README.md
pyproject.toml
setup.cfg
setup.py
MHTMLconverter.egg-info/PKG-INFO
MHTMLconverter.egg-info/SOURCES.txt
MHTMLconverter.egg-info/dependency_links.txt
MHTMLconverter.egg-info/entry_points.txt
MHTMLconverter.egg-info/requires.txt
MHTMLconverter.egg-info/top_level.txt
mhtmlconverter/__init__.py
mhtmlconverter/fileutility.py
mhtmlconverter/htmlutility.py
mhtmlconverter/mhtml.py
mhtmlconverter.egg-info/PKG-INFO
mhtmlconverter.egg-info/SOURCES.txt
mhtmlconverter.egg-info/dependency_links.txt
mhtmlconverter.egg-info/requires.txt
mhtmlconverter.egg-info/top_level.txt
mhtmlconverter/cli/__init__.py
mhtmlconverter/cli/html2mhtml.py
mhtmlconverter/cli/md2mhtml.py
mhtmlconverter/cli/mhtml2html.py
tests/test_fileutility.py
tests/test_html.py
tests/test_md.py
tests/test_mhtml.py