Metadata-Version: 2.1
Name: MHTMLconverter
Version: 0.5
Summary: Tools to convert markdown or html files including images to a single MHTML self-content file
Home-page: https://github.com/arnaudrevel/MHTMLconverter
Author: Arnaud Revel
Author-email: revel.arnaud@gmail.com
Requires-Python: >=3.9
